{
    "TO DO" : [
        {
            "datasets" : [
                {
                    "configsuite" : "BasicConfig",
                    "runtag" : "Feb_22_2026",
                    "name" : "Pythia_inclusive",
                    "table" : "parts",
                    "objsyst" : "NO_PVCUT",
                    "location" : "scratch-submit",
                    "dsetkind": "pq",
                    "color_override" : "k",
                    "label_override" : "",
                    "extra_cuts" : [
                    ]
                }
            ],
            "variables" : [
                "var::ProfileVariable('matchPt', var::DeltaRVariable('matchEta', 'matchPhi', 'eta', 'phi'), 'percentile', 99)"
            ],
            "extras" : [
                "func::TrackAngularResolution(0.01, 0.01)"
            ],
            "override_filenames" : [
                "dR_99th_percentile_vs_pt_with_fit"
            ],
            "weights" : [
                "wt_nominal"
            ],
            "cut" : [
                "cut::GreaterThanCut('puppiWeight', 0.99)",
                "cut::LessThanCut(var::AbsVariable('dz'), 0.2)",
                "cut::EqualsCut('nMatches', 1)"
            ],
            "binning" : "auto",
            "plotspath" : "ANplots/matching/",
            "plotsprefix" : "",
            "driver" : "plot_histogram",
            "nopad" : true,
            "force_range" : [0.5, 100],
            "logy" : false
        },
        {
            "datasets" : [
                {
                    "configsuite" : "BasicConfig",
                    "runtag" : "Feb_22_2026",
                    "name" : "Pythia_inclusive",
                    "table" : "parts",
                    "objsyst" : "nominal",
                    "location" : "scratch-submit",
                    "dsetkind": "pq",
                    "color_override" : "blue",
                    "label_override" : "Gen-level $\\mu^\\pm$, matched with reco-level $h^\\pm$",
                    "extra_cuts" : [
                        "cut::EqualsCut('pdgid', 211)",
                        "cut::EqualsCut('matchTypes', 1)"
                    ]
                },
                {
                    "configsuite" : "BasicConfig",
                    "runtag" : "Feb_22_2026",
                    "name" : "Pythia_inclusive",
                    "table" : "parts",
                    "objsyst" : "nominal",
                    "location" : "scratch-submit",
                    "dsetkind": "pq",
                    "color_override" : "red",
                    "label_override" : "Gen-level $\\mu^\\pm$, matched with reco-level $e^\\pm$",
                    "extra_cuts" : [
                        "cut::EqualsCut('pdgid', 11)",
                        "cut::EqualsCut('matchTypes', 1)"
                    ]
                },
                {
                    "configsuite" : "BasicConfig",
                    "runtag" : "Feb_22_2026",
                    "name" : "Pythia_inclusive",
                    "table" : "parts",
                    "objsyst" : "nominal",
                    "location" : "scratch-submit",
                    "dsetkind": "pq",
                    "color_override" : "magenta",
                    "label_override" : "Gen-level $\\mu^\\pm$, matched with reco-level $\\mu^\\pm$",
                    "extra_cuts" : [
                        "cut::EqualsCut('pdgid', 13)",
                        "cut::EqualsCut('matchTypes', 1)"
                    ]
                }
            ],
            "variables" : [
                "var::RelativeResolutionVariable('matchPt', 'pt')"
            ],
            "override_filenames" : [
                "gen_muon_pt_resolution_by_reco_match_type"
            ],
            "weights" : [
                "wt_nominal"
            ],
            "cut" : [
                "cut::GreaterThanCut('matchPt', 0.5)"
            ],
            "binning" : "auto",
            "plotspath" : "ANplots/matching/",
            "plotsprefix" : "",
            "driver" : "plot_histogram",
            "nopad" : true,
            "density" : true,
            "force_range" : [-0.5, 0.5]
        },
        {
            "datasets" : [
                {
                    "configsuite" : "BasicConfig",
                    "runtag" : "Feb_22_2026",
                    "name" : "Pythia_inclusive",
                    "table" : "parts",
                    "objsyst" : "nominal",
                    "location" : "scratch-submit",
                    "dsetkind": "pq",
                    "color_override" : "blue",
                    "label_override" : "Gen-level $e^\\pm$, matched with reco-level $h^\\pm$",
                    "extra_cuts" : [
                        "cut::EqualsCut('pdgid', 211)",
                        "cut::EqualsCut('matchTypes', 2)"
                    ]
                },
                {
                    "configsuite" : "BasicConfig",
                    "runtag" : "Feb_22_2026",
                    "name" : "Pythia_inclusive",
                    "table" : "parts",
                    "objsyst" : "nominal",
                    "location" : "scratch-submit",
                    "dsetkind": "pq",
                    "color_override" : "red",
                    "label_override" : "Gen-level $e^\\pm$, matched with reco-level $e^\\pm$",
                    "extra_cuts" : [
                        "cut::EqualsCut('pdgid', 11)",
                        "cut::EqualsCut('matchTypes', 2)"
                    ]
                },
                {
                    "configsuite" : "BasicConfig",
                    "runtag" : "Feb_22_2026",
                    "name" : "Pythia_inclusive",
                    "table" : "parts",
                    "objsyst" : "nominal",
                    "location" : "scratch-submit",
                    "dsetkind": "pq",
                    "color_override" : "magenta",
                    "label_override" : "Gen-level $e^\\pm$, matched with reco-level $\\mu^\\pm$",
                    "extra_cuts" : [
                        "cut::EqualsCut('pdgid', 13)",
                        "cut::EqualsCut('matchTypes', 2)"
                    ]
                }
            ],
            "variables" : [
                "var::RelativeResolutionVariable('matchPt', 'pt')"
            ],
            "override_filenames" : [
                "gen_electron_pt_resolution_by_reco_match_type"
            ],
            "weights" : [
                "wt_nominal"
            ],
            "cut" : [
                "cut::GreaterThanCut('matchPt', 0.5)"
            ],
            "binning" : "auto",
            "plotspath" : "ANplots/matching/",
            "plotsprefix" : "",
            "driver" : "plot_histogram",
            "nopad" : true,
            "density" : true,
            "force_range" : [-0.5, 0.5]
        },
        {
            "datasets" : [
                {
                    "configsuite" : "BasicConfig",
                    "runtag" : "Feb_22_2026",
                    "name" : "Pythia_inclusive",
                    "table" : "parts",
                    "objsyst" : "nominal",
                    "location" : "scratch-submit",
                    "dsetkind": "pq",
                    "color_override" : "blue",
                    "label_override" : "Gen-level $h^\\pm$, matched with reco-level $h^\\pm$",
                    "extra_cuts" : [
                        "cut::EqualsCut('pdgid', 211)",
                        "cut::EqualsCut('matchTypes', 8)"
                    ]
                },
                {
                    "configsuite" : "BasicConfig",
                    "runtag" : "Feb_22_2026",
                    "name" : "Pythia_inclusive",
                    "table" : "parts",
                    "objsyst" : "nominal",
                    "location" : "scratch-submit",
                    "dsetkind": "pq",
                    "color_override" : "red",
                    "label_override" : "Gen-level $h^\\pm$, matched with reco-level $e^\\pm$",
                    "extra_cuts" : [
                        "cut::EqualsCut('pdgid', 11)",
                        "cut::EqualsCut('matchTypes', 8)"
                    ]
                },
                {
                    "configsuite" : "BasicConfig",
                    "runtag" : "Feb_22_2026",
                    "name" : "Pythia_inclusive",
                    "table" : "parts",
                    "objsyst" : "nominal",
                    "location" : "scratch-submit",
                    "dsetkind": "pq",
                    "color_override" : "magenta",
                    "label_override" : "Gen-level $h^\\pm$, matched with reco-level $\\mu^\\pm$",
                    "extra_cuts" : [
                        "cut::EqualsCut('pdgid', 13)",
                        "cut::EqualsCut('matchTypes', 8)"
                    ]
                }
            ],
            "variables" : [
                "var::RelativeResolutionVariable('matchPt', 'pt')"
            ],
            "override_filenames" : [
                "gen_hadch_pt_resolution_by_reco_match_type"
            ],
            "weights" : [
                "wt_nominal"
            ],
            "cut" : [
                "cut::GreaterThanCut('matchPt', 0.5)"
            ],
            "binning" : "auto",
            "plotspath" : "ANplots/matching/",
            "plotsprefix" : "",
            "driver" : "plot_histogram",
            "nopad" : true,
            "density" : true,
            "force_range" : [-0.5, 0.5]
        },
        {
            "datasets" : [
                {
                    "configsuite" : "BasicConfig",
                    "runtag" : "Feb_22_2026",
                    "name" : "Pythia_inclusive",
                    "table" : "jets",
                    "objsyst" : "nominal",
                    "location" : "scratch-submit",
                    "dsetkind": "pq",
                    "color_override" : "blue",
                    "label_override" : "$30 < p_{T}^{gen} < 100$ GeV",
                    "extra_cuts" : [
                        "cut::TwoSidedCut('matchedPt', 30, 100)"
                    ]
                },
                {
                    "configsuite" : "BasicConfig",
                    "runtag" : "Feb_22_2026",
                    "name" : "Pythia_inclusive",
                    "table" : "jets",
                    "objsyst" : "nominal",
                    "location" : "scratch-submit",
                    "dsetkind": "pq",
                    "color_override" : "magenta",
                    "label_override" : "$100 < p_{T}^{gen} < 200$ GeV",
                    "extra_cuts" : [
                        "cut::TwoSidedCut('matchedPt', 100, 200)"
                    ]
                },
                {
                    "configsuite" : "BasicConfig",
                    "runtag" : "Feb_22_2026",
                    "name" : "Pythia_inclusive",
                    "table" : "jets",
                    "objsyst" : "nominal",
                    "location" : "scratch-submit",
                    "dsetkind": "pq",
                    "color_override" : "orange",
                    "label_override" : "$ 200 < p_{T}^{gen} < 500$ GeV",
                    "extra_cuts" : [
                        "cut::TwoSidedCut('matchedPt', 200, 500)"
                    ]
                },
                {
                    "configsuite" : "BasicConfig",
                    "runtag" : "Feb_22_2026",
                    "name" : "Pythia_inclusive",
                    "table" : "jets",
                    "objsyst" : "nominal",
                    "location" : "scratch-submit",
                    "dsetkind": "pq",
                    "color_override" : "red",
                    "label_override" : "$p_{T}^{gen} > 500$ GeV",
                    "extra_cuts" : [
                        "cut::GreaterThanCut('matchedPt', 500)"
                    ]
                }
            ],
            "variables" : [
                "var::DeltaRVariable('matchedEta', 'matchedPhi', 'Jeta', 'Jphi')"
            ],
            "override_filenames" : [
                "jet_dR_resolution_binned_by_gen_pt"
            ],
            "weights" : [
                "wt_nominal"
            ],
            "cut" : [
            ],
            "binning" : "auto",
            "plotspath" : "ANplots/matching/",
            "plotsprefix" : "",
            "driver" : "plot_histogram",
            "nopad" : true,
            "density" : true
        },
        {
            "datasets" : [
                {
                    "configsuite" : "BasicConfig",
                    "runtag" : "Feb_22_2026",
                    "name" : "Pythia_inclusive",
                    "table" : "jets",
                    "objsyst" : "nominal",
                    "location" : "scratch-submit",
                    "dsetkind": "pq",
                    "color_override" : "k",
                    "label_override" : "",
                    "extra_cuts" : [
                        
                    ]
                }
            ],
            "variables" : [
                "var::RateVariable('matched', 'matchedPt')"
            ],
            "override_filenames" : [
                "jet_matching_efficiency_vs_pt"
            ],
            "weights" : [
                "wt_nominal"
            ],
            "cut" : [
            ],
            "binning" : "auto",
            "plotspath" : "ANplots/matching/",
            "plotsprefix" : "",
            "driver" : "plot_histogram",
            "nopad" : true
        },
        {
            "datasets" : [
                {
                    "configsuite" : "BasicConfig",
                    "runtag" : "Feb_22_2026",
                    "name" : "Pythia_inclusive",
                    "table" : "jets",
                    "objsyst" : "nominal",
                    "location" : "scratch-submit",
                    "dsetkind": "pq",
                    "color_override" : "blue",
                    "label_override" : "$30 < p_{T}^{gen} < 100$ GeV",
                    "extra_cuts" : [
                        "cut::TwoSidedCut('matchedPt', 30, 100)"
                    ]
                },
                {
                    "configsuite" : "BasicConfig",
                    "runtag" : "Feb_22_2026",
                    "name" : "Pythia_inclusive",
                    "table" : "jets",
                    "objsyst" : "nominal",
                    "location" : "scratch-submit",
                    "dsetkind": "pq",
                    "color_override" : "magenta",
                    "label_override" : "$100 < p_{T}^{gen} < 200$ GeV",
                    "extra_cuts" : [
                        "cut::TwoSidedCut('matchedPt', 100, 200)"
                    ]
                },
                {
                    "configsuite" : "BasicConfig",
                    "runtag" : "Feb_22_2026",
                    "name" : "Pythia_inclusive",
                    "table" : "jets",
                    "objsyst" : "nominal",
                    "location" : "scratch-submit",
                    "dsetkind": "pq",
                    "color_override" : "orange",
                    "label_override" : "$ 200 < p_{T}^{gen} < 500$ GeV",
                    "extra_cuts" : [
                        "cut::TwoSidedCut('matchedPt', 200, 500)"
                    ]
                },
                {
                    "configsuite" : "BasicConfig",
                    "runtag" : "Feb_22_2026",
                    "name" : "Pythia_inclusive",
                    "table" : "jets",
                    "objsyst" : "nominal",
                    "location" : "scratch-submit",
                    "dsetkind": "pq",
                    "color_override" : "red",
                    "label_override" : "$p_{T}^{gen} > 500$ GeV",
                    "extra_cuts" : [
                        "cut::GreaterThanCut('matchedPt', 500)"
                    ]
                }
            ],
            "variables" : [
                "var::RelativeResolutionVariable('matchedPt', 'Jpt')"
            ],
            "override_filenames" : [
                "jet_pt_resolution_binned_by_gen_pt"
            ],
            "weights" : [
                "wt_nominal"
            ],
            "cut" : [
            ],
            "binning" : "auto",
            "plotspath" : "ANplots/matching/",
            "plotsprefix" : "",
            "driver" : "plot_histogram",
            "nopad" : true,
            "density" : true,
            "force_range" : [-1.0, 1.0]
        },
        {
            "datasets" : [
                {
                    "configsuite" : "BasicConfig",
                    "runtag" : "Feb_22_2026",
                    "name" : "Pythia_inclusive",
                    "table" : "parts",
                    "objsyst" : "NO_PVCUT",
                    "location" : "scratch-submit",
                    "dsetkind": "pq",
                    "color_override" : "k",
                    "label_override" : "",
                    "extra_cuts" : [
                        
                    ]
                }
            ],
            "variables" : [
                "var::ProfileVariable('matchPt', var::RelativeResolutionVariable('matchPt','pt'), 'percentile-range', [16, 84])"
            ],
            "extras" : [
                "func::TrackPtResolution(0.03, 0.001)"
            ],
            "override_filenames" : [
                "dpt_68th_percentile_vs_pt_with_fit"
            ],
            "weights" : [
                "wt_nominal"
            ],
            "cut" : [
                "cut::GreaterThanCut('puppiWeight', 0.99)",
                "cut::LessThanCut(var::AbsVariable('dz'), 0.2)",
                "cut::EqualsCut('nMatches', 1)"
            ],
            "binning" : "auto",
            "plotspath" : "ANplots/matching/",
            "plotsprefix" : "",
            "driver" : "plot_histogram",
            "nopad" : true,
            "force_range" : [0.5, 500],
            "logy" : false
        },
        {
            "datasets" : [
                {
                    "configsuite" : "BasicConfig",
                    "runtag" : "Feb_22_2026",
                    "name" : "Pythia_inclusive",
                    "table" : "parts",
                    "objsyst" : "NO_PVCUT",
                    "location" : "scratch-submit",
                    "dsetkind": "pq",
                    "color_override" : "k",
                    "label_override" : "",
                    "extra_cuts" : [
                    ]
                }
            ],
            "variables" : [
                "var::ProfileVariable('matchPt', var::DeltaRVariable('matchEta', 'matchPhi', 'eta', 'phi'), 'percentile', 68)"
            ],
            "extras" : [
                "func::TrackAngularResolution(0.0003, 0.003)"
            ],
            "override_filenames" : [
                "dR_68th_percentile_vs_pt_with_fit"
            ],
            "weights" : [
                "wt_nominal"
            ],
            "cut" : [
                "cut::GreaterThanCut('puppiWeight', 0.99)",
                "cut::LessThanCut(var::AbsVariable('dz'), 0.2)",
                "cut::EqualsCut('nMatches', 1)"
            ],
            "binning" : "auto",
            "plotspath" : "ANplots/matching/",
            "plotsprefix" : "",
            "driver" : "plot_histogram",
            "nopad" : true,
            "force_range" : [0.5, 100],
            "logy" : false
        },
        {
            "datasets" : [
                {
                    "configsuite" : "BasicConfig",
                    "runtag" : "Feb_22_2026",
                    "name" : "Pythia_inclusive",
                    "table" : "parts",
                    "objsyst" : "NO_PVCUT",
                    "location" : "scratch-submit",
                    "dsetkind": "pq",
                    "color_override" : "blue",
                    "label_override" : "$0 < p_{T}^{gen} < 0.5$ GeV",
                    "extra_cuts" : [
                        "cut::TwoSidedCut('matchPt', 0, 0.5)"
                    ]
                },
                {
                    "configsuite" : "BasicConfig",
                    "runtag" : "Feb_22_2026",
                    "name" : "Pythia_inclusive",
                    "table" : "parts",
                    "objsyst" : "NO_PVCUT",
                    "location" : "scratch-submit",
                    "dsetkind": "pq",
                    "color_override" : "magenta",
                    "label_override" : "$0.5 < p_{T}^{gen} < 1$ GeV",
                    "extra_cuts" : [
                        "cut::TwoSidedCut('matchPt', 0.5, 1)"
                    ]
                },
                {
                    "configsuite" : "BasicConfig",
                    "runtag" : "Feb_22_2026",
                    "name" : "Pythia_inclusive",
                    "table" : "parts",
                    "objsyst" : "NO_PVCUT",
                    "location" : "scratch-submit",
                    "dsetkind": "pq",
                    "color_override" : "yellow",
                    "label_override" : "$1 < p_{T}^{gen} < 2$ GeV",
                    "extra_cuts" : [
                        "cut::TwoSidedCut('matchPt', 1, 2)"
                    ]
                },
                {
                    "configsuite" : "BasicConfig",
                    "runtag" : "Feb_22_2026",
                    "name" : "Pythia_inclusive",
                    "table" : "parts",
                    "objsyst" : "NO_PVCUT",
                    "location" : "scratch-submit",
                    "dsetkind": "pq",
                    "color_override" : "orange",
                    "label_override" : "$2 < p_{T}^{gen} < 5$ GeV",
                    "extra_cuts" : [
                        "cut::TwoSidedCut('matchPt', 2, 5)"
                    ]
                },
                {
                    "configsuite" : "BasicConfig",
                    "runtag" : "Feb_22_2026",
                    "name" : "Pythia_inclusive",
                    "table" : "parts",
                    "objsyst" : "NO_PVCUT",
                    "location" : "scratch-submit",
                    "dsetkind": "pq",
                    "color_override" : "red",
                    "label_override" : "$5 < p_{T}^{gen} < 10$ GeV",
                    "extra_cuts" : [
                        "cut::TwoSidedCut('matchPt', 5, 10)"
                    ]
                },
                {
                    "configsuite" : "BasicConfig",
                    "runtag" : "Feb_22_2026",
                    "name" : "Pythia_inclusive",
                    "table" : "parts",
                    "objsyst" : "NO_PVCUT",
                    "location" : "scratch-submit",
                    "dsetkind": "pq",
                    "color_override" : "purple",
                    "label_override" : "$10 < p_{T}^{gen} < 20$ GeV",
                    "extra_cuts" : [
                        "cut::TwoSidedCut('matchPt', 10, 20)"
                    ]
                },
                {
                    "configsuite" : "BasicConfig",
                    "runtag" : "Feb_22_2026",
                    "name" : "Pythia_inclusive",
                    "table" : "parts",
                    "objsyst" : "NO_PVCUT",
                    "location" : "scratch-submit",
                    "dsetkind": "pq",
                    "color_override" : "brown",
                    "label_override" : "$20 < p_{T}^{gen} < 50$ GeV",
                    "extra_cuts" : [
                        "cut::TwoSidedCut('matchPt', 20, 50)"
                    ]
                }
            ],
            "variables" : [
                "var::DeltaRVariable('matchEta', 'matchPhi', 'eta', 'phi')"
            ],
            "override_filenames" : [
                "dR_binned_by_pt"
            ],
            "weights" : [
                "wt_nominal"
            ],
            "cut" : [
                "cut::GreaterThanCut('puppiWeight', 0.99)",
                "cut::LessThanCut(var::AbsVariable('dz'), 0.2)",
                "cut::EqualsCut('nMatches', 1)"
            ],
            "binning" : "auto",
            "plotspath" : "ANplots/matching/",
            "plotsprefix" : "",
            "driver" : "plot_histogram",
            "nopad" : true
        },
        {
            "datasets" : [
                {
                    "configsuite" : "BasicConfig",
                    "runtag" : "Feb_22_2026",
                    "name" : "Pythia_inclusive",
                    "table" : "parts",
                    "objsyst" : "NO_PVCUT",
                    "location" : "scratch-submit",
                    "dsetkind": "pq",
                    "color_override" : "blue",
                    "label_override" : "$0 < \\Delta R < 0.02$",
                    "extra_cuts" : [
                        "cut::TwoSidedCut(var::DeltaRVariable('matchEta', 'matchPhi', 'eta', 'phi'), 0, 0.02)"
                    ]
                },
                {
                    "configsuite" : "BasicConfig",
                    "runtag" : "Feb_22_2026",
                    "name" : "Pythia_inclusive",
                    "table" : "parts",
                    "objsyst" : "NO_PVCUT",
                    "location" : "scratch-submit",
                    "dsetkind": "pq",
                    "color_override" : "magenta",
                    "label_override" : "$0.02 < \\Delta R < 0.04$",
                    "extra_cuts" : [
                        "cut::TwoSidedCut(var::DeltaRVariable('matchEta', 'matchPhi', 'eta', 'phi'), 0.02, 0.04)"
                    ]
                },
                {
                    "configsuite" : "BasicConfig",
                    "runtag" : "Feb_22_2026",
                    "name" : "Pythia_inclusive",
                    "table" : "parts",
                    "objsyst" : "NO_PVCUT",
                    "location" : "scratch-submit",
                    "dsetkind": "pq",
                    "color_override" : "yellow",
                    "label_override" : "$0.04 < \\Delta R < 0.06$",
                    "extra_cuts" : [
                        "cut::TwoSidedCut(var::DeltaRVariable('matchEta', 'matchPhi', 'eta', 'phi'), 0.04, 0.06)"
                    ]
                },
                {
                    "configsuite" : "BasicConfig",
                    "runtag" : "Feb_22_2026",
                    "name" : "Pythia_inclusive",
                    "table" : "parts",
                    "objsyst" : "NO_PVCUT",
                    "location" : "scratch-submit",
                    "dsetkind": "pq",
                    "color_override" : "orange",
                    "label_override" : "$0.06 < \\Delta R < 0.08$",
                    "extra_cuts" : [
                        "cut::TwoSidedCut(var::DeltaRVariable('matchEta', 'matchPhi', 'eta', 'phi'), 0.06, 0.08)"
                    ]
                },
                {
                    "configsuite" : "BasicConfig",
                    "runtag" : "Feb_22_2026",
                    "name" : "Pythia_inclusive",
                    "table" : "parts",
                    "objsyst" : "NO_PVCUT",
                    "location" : "scratch-submit",
                    "dsetkind": "pq",
                    "color_override" : "red",
                    "label_override" : "$0.08 < \\Delta R < 0.1$",
                    "extra_cuts" : [
                        "cut::TwoSidedCut(var::DeltaRVariable('matchEta', 'matchPhi', 'eta', 'phi'), 0.08, 0.1)"
                    ]
                }
            ],
            "variables" : [
                "var::RelativeResolutionVariable('matchPt','pt')"
            ],
            "override_filenames" : [
                "dpt_binned_by_dR_0pt0.5"
            ],
            "weights" : [
                "wt_nominal"
            ],
            "cut" : [
                "cut::GreaterThanCut('puppiWeight', 0.99)",
                "cut::LessThanCut(var::AbsVariable('dz'), 0.2)",
                "cut::EqualsCut('nMatches', 1)",
                "cut::TwoSidedCut('matchPt', 0, 0.5)"
            ],
            "binning" : "auto",
            "plotspath" : "ANplots/matching/",
            "plotsprefix" : "",
            "driver" : "plot_histogram",
            "nopad" : true,
            "logy" : false,
            "force_range" : [-0.5, 0.5],
            "density" : true
        },
        {
            "datasets" : [
                {
                    "configsuite" : "BasicConfig",
                    "runtag" : "Feb_22_2026",
                    "name" : "Pythia_inclusive",
                    "table" : "parts",
                    "objsyst" : "NO_PVCUT",
                    "location" : "scratch-submit",
                    "dsetkind": "pq",
                    "color_override" : "blue",
                    "label_override" : "$0 < \\Delta R < 0.02$",
                    "extra_cuts" : [
                        "cut::TwoSidedCut(var::DeltaRVariable('matchEta', 'matchPhi', 'eta', 'phi'), 0, 0.02)"
                    ]
                },
                {
                    "configsuite" : "BasicConfig",
                    "runtag" : "Feb_22_2026",
                    "name" : "Pythia_inclusive",
                    "table" : "parts",
                    "objsyst" : "NO_PVCUT",
                    "location" : "scratch-submit",
                    "dsetkind": "pq",
                    "color_override" : "magenta",
                    "label_override" : "$0.02 < \\Delta R < 0.04$",
                    "extra_cuts" : [
                        "cut::TwoSidedCut(var::DeltaRVariable('matchEta', 'matchPhi', 'eta', 'phi'), 0.02, 0.04)"
                    ]
                },
                {
                    "configsuite" : "BasicConfig",
                    "runtag" : "Feb_22_2026",
                    "name" : "Pythia_inclusive",
                    "table" : "parts",
                    "objsyst" : "NO_PVCUT",
                    "location" : "scratch-submit",
                    "dsetkind": "pq",
                    "color_override" : "yellow",
                    "label_override" : "$0.04 < \\Delta R < 0.06$",
                    "extra_cuts" : [
                        "cut::TwoSidedCut(var::DeltaRVariable('matchEta', 'matchPhi', 'eta', 'phi'), 0.04, 0.06)"
                    ]
                },
                {
                    "configsuite" : "BasicConfig",
                    "runtag" : "Feb_22_2026",
                    "name" : "Pythia_inclusive",
                    "table" : "parts",
                    "objsyst" : "NO_PVCUT",
                    "location" : "scratch-submit",
                    "dsetkind": "pq",
                    "color_override" : "orange",
                    "label_override" : "$0.06 < \\Delta R < 0.08$",
                    "extra_cuts" : [
                        "cut::TwoSidedCut(var::DeltaRVariable('matchEta', 'matchPhi', 'eta', 'phi'), 0.06, 0.08)"
                    ]
                },
                {
                    "configsuite" : "BasicConfig",
                    "runtag" : "Feb_22_2026",
                    "name" : "Pythia_inclusive",
                    "table" : "parts",
                    "objsyst" : "NO_PVCUT",
                    "location" : "scratch-submit",
                    "dsetkind": "pq",
                    "color_override" : "red",
                    "label_override" : "$0.08 < \\Delta R < 0.1$",
                    "extra_cuts" : [
                        "cut::TwoSidedCut(var::DeltaRVariable('matchEta', 'matchPhi', 'eta', 'phi'), 0.08, 0.1)"
                    ]
                }
            ],
            "variables" : [
                "var::RelativeResolutionVariable('matchPt','pt')"
            ],
            "override_filenames" : [
                "dpt_binned_by_dR_0.5pt1.0"
            ],
            "weights" : [
                "wt_nominal"
            ],
            "cut" : [
                "cut::GreaterThanCut('puppiWeight', 0.99)",
                "cut::LessThanCut(var::AbsVariable('dz'), 0.2)",
                "cut::EqualsCut('nMatches', 1)",
                "cut::TwoSidedCut('matchPt', 0.5, 1.0)"
            ],
            "binning" : "auto",
            "plotspath" : "ANplots/matching/",
            "plotsprefix" : "",
            "driver" : "plot_histogram",
            "nopad" : true,
            "logy" : false,
            "force_range" : [-0.5, 0.5],
            "density" : true
        },
        {
            "datasets" : [
                {
                    "configsuite" : "BasicConfig",
                    "runtag" : "Feb_22_2026",
                    "name" : "Pythia_inclusive",
                    "table" : "parts",
                    "objsyst" : "NO_PVCUT",
                    "location" : "scratch-submit",
                    "dsetkind": "pq",
                    "color_override" : "blue",
                    "label_override" : "$0 < p_{T}^{gen} < 0.5$ GeV",
                    "extra_cuts" : [
                        "cut::TwoSidedCut('matchPt', 0, 0.5)"
                    ]
                },
                {
                    "configsuite" : "BasicConfig",
                    "runtag" : "Feb_22_2026",
                    "name" : "Pythia_inclusive",
                    "table" : "parts",
                    "objsyst" : "NO_PVCUT",
                    "location" : "scratch-submit",
                    "dsetkind": "pq",
                    "color_override" : "magenta",
                    "label_override" : "$0.5 < p_{T}^{gen} < 1$ GeV",
                    "extra_cuts" : [
                        "cut::TwoSidedCut('matchPt', 0.5, 1)"
                    ]
                },
                {
                    "configsuite" : "BasicConfig",
                    "runtag" : "Feb_22_2026",
                    "name" : "Pythia_inclusive",
                    "table" : "parts",
                    "objsyst" : "NO_PVCUT",
                    "location" : "scratch-submit",
                    "dsetkind": "pq",
                    "color_override" : "yellow",
                    "label_override" : "$1 < p_{T}^{gen} < 2$ GeV",
                    "extra_cuts" : [
                        "cut::TwoSidedCut('matchPt', 1, 2)"
                    ]
                },
                {
                    "configsuite" : "BasicConfig",
                    "runtag" : "Feb_22_2026",
                    "name" : "Pythia_inclusive",
                    "table" : "parts",
                    "objsyst" : "NO_PVCUT",
                    "location" : "scratch-submit",
                    "dsetkind": "pq",
                    "color_override" : "orange",
                    "label_override" : "$2 < p_{T}^{gen} < 5$ GeV",
                    "extra_cuts" : [
                        "cut::TwoSidedCut('matchPt', 2, 5)"
                    ]
                },
                {
                    "configsuite" : "BasicConfig",
                    "runtag" : "Feb_22_2026",
                    "name" : "Pythia_inclusive",
                    "table" : "parts",
                    "objsyst" : "NO_PVCUT",
                    "location" : "scratch-submit",
                    "dsetkind": "pq",
                    "color_override" : "red",
                    "label_override" : "$5 < p_{T}^{gen} < 10$ GeV",
                    "extra_cuts" : [
                        "cut::TwoSidedCut('matchPt', 5, 10)"
                    ]
                }
            ],
            "variables" : [
                "var::ProfileVariable(var::DeltaRVariable('matchEta', 'matchPhi', 'eta', 'phi'), var::RelativeResolutionVariable('matchPt','pt'), 'median')",
                "var::ProfileVariable(var::DeltaRVariable('matchEta', 'matchPhi', 'eta', 'phi'), var::RelativeResolutionVariable('matchPt','pt'), 'percentile-range', [16, 84])",
                "var::ProfileVariable(var::DeltaRVariable('matchEta', 'matchPhi', 'eta', 'phi'), var::RelativeResolutionVariable('matchPt','pt'), 'percentile-range', [2.5, 97.5])",
                "var::ProfileVariable(var::DeltaRVariable('matchEta', 'matchPhi', 'eta', 'phi'), var::RelativeResolutionVariable('matchPt','pt'), 'percentile-range', [0.5, 99.5])"
            ],
            "override_filenames" : [
                "median_dpt_vs_dR",
                "sigma68_dpt_vs_dR",
                "sigma95_dpt_vs_dR",
                "sigma99_dpt_vs_dR"
            ],
            "weights" : [
                "wt_nominal"
            ],
            "cut" : [
                "cut::GreaterThanCut('puppiWeight', 0.99)",
                "cut::LessThanCut(var::AbsVariable('dz'), 0.2)",
                "cut::EqualsCut('nMatches', 1)"
            ],
            "binning" : "auto",
            "plotspath" : "ANplots/matching/",
            "plotsprefix" : "",
            "driver" : "plot_histogram",
            "nopad" : true,
            "logy" : false
        },
        {
            "datasets" : [
                {
                    "configsuite" : "BasicConfig",
                    "runtag" : "Feb_22_2026",
                    "name" : "Pythia_inclusive",
                    "table" : "parts",
                    "objsyst" : "NO_PVCUT",
                    "location" : "scratch-submit",
                    "dsetkind": "pq",
                    "color_override" : "k",
                    "label_override" : "",
                    "extra_cuts" : [
                    ]
                }
            ],
            "variables" : [
                "var::ProfileVariable('matchPt', var::RelativeResolutionVariable('matchPt','pt'), 'median')",
                "var::ProfileVariable('matchPt', var::RelativeResolutionVariable('matchPt','pt'), 'std')",
                "var::ProfileVariable('matchPt', var::RelativeResolutionVariable('matchPt','pt'), 'percentile-range', [16, 84])",
                "var::ProfileVariable('matchPt', var::RelativeResolutionVariable('matchPt','pt'), 'percentile-range', [2.5, 97.5])",
                "var::ProfileVariable('matchPt', var::RelativeResolutionVariable('matchPt','pt'), 'percentile-range', [0.5, 99.5])",

                "var::ProfileVariable('matchPt', var::DeltaRVariable('matchEta', 'matchPhi', 'eta', 'phi'), 'median')",
                "var::ProfileVariable('matchPt', var::DeltaRVariable('matchEta', 'matchPhi', 'eta', 'phi'), 'std')",
                "var::ProfileVariable('matchPt', var::DeltaRVariable('matchEta', 'matchPhi', 'eta', 'phi'), 'percentile', 68)",
                "var::ProfileVariable('matchPt', var::DeltaRVariable('matchEta', 'matchPhi', 'eta', 'phi'), 'percentile', 95)",
                "var::ProfileVariable('matchPt', var::DeltaRVariable('matchEta', 'matchPhi', 'eta', 'phi'), 'percentile', 99)"
            ],
            "override_filenames" : [
                "median_dpt_vs_pt",
                "std_dpt_vs_pt",
                "sigma68_dpt_vs_pt",
                "sigma95_dpt_vs_pt",
                "sigma99_dpt_vs_pt",

                "median_dR_vs_pt",
                "std_dR_vs_pt",
                "dR_68th_percentile_vs_pt",
                "dR_95th_percentile_vs_pt",
                "dR_99th_percentile_vs_pt"
            ],
            "weights" : [
                "wt_nominal"
            ],
            "cut" : [
                "cut::GreaterThanCut('puppiWeight', 0.99)",
                "cut::LessThanCut(var::AbsVariable('dz'), 0.2)",
                "cut::EqualsCut('nMatches', 1)"
            ],
            "binning" : "auto",
            "plotspath" : "ANplots/matching/",
            "plotsprefix" : "",
            "driver" : "plot_histogram",
            "nopad" : true,
            "force_range" : [0.5, 100],
            "logy" : false
        },
        {
            "datasets" : [
                {
                    "configsuite" : "BasicConfig",
                    "runtag" : "Feb_22_2026",
                    "name" : "Pythia_inclusive",
                    "table" : "parts",
                    "objsyst" : "NO_PVCUT",
                    "location" : "scratch-submit",
                    "dsetkind": "pq",
                    "color_override" : "blue",
                    "label_override" : "$0 < p_{T}^{gen} < 0.5$ GeV",
                    "extra_cuts" : [
                        "cut::TwoSidedCut('matchPt', 0, 0.5)"
                    ]
                },
                {
                    "configsuite" : "BasicConfig",
                    "runtag" : "Feb_22_2026",
                    "name" : "Pythia_inclusive",
                    "table" : "parts",
                    "objsyst" : "NO_PVCUT",
                    "location" : "scratch-submit",
                    "dsetkind": "pq",
                    "color_override" : "magenta",
                    "label_override" : "$0.5 < p_{T}^{gen} < 1$ GeV",
                    "extra_cuts" : [
                        "cut::TwoSidedCut('matchPt', 0.5, 1)"
                    ]
                },
                {
                    "configsuite" : "BasicConfig",
                    "runtag" : "Feb_22_2026",
                    "name" : "Pythia_inclusive",
                    "table" : "parts",
                    "objsyst" : "NO_PVCUT",
                    "location" : "scratch-submit",
                    "dsetkind": "pq",
                    "color_override" : "yellow",
                    "label_override" : "$1 < p_{T}^{gen} < 2$ GeV",
                    "extra_cuts" : [
                        "cut::TwoSidedCut('matchPt', 1, 2)"
                    ]
                },
                {
                    "configsuite" : "BasicConfig",
                    "runtag" : "Feb_22_2026",
                    "name" : "Pythia_inclusive",
                    "table" : "parts",
                    "objsyst" : "NO_PVCUT",
                    "location" : "scratch-submit",
                    "dsetkind": "pq",
                    "color_override" : "orange",
                    "label_override" : "$2 < p_{T}^{gen} < 5$ GeV",
                    "extra_cuts" : [
                        "cut::TwoSidedCut('matchPt', 2, 5)"
                    ]
                },
                {
                    "configsuite" : "BasicConfig",
                    "runtag" : "Feb_22_2026",
                    "name" : "Pythia_inclusive",
                    "table" : "parts",
                    "objsyst" : "NO_PVCUT",
                    "location" : "scratch-submit",
                    "dsetkind": "pq",
                    "color_override" : "red",
                    "label_override" : "$5 < p_{T}^{gen} < 10$ GeV",
                    "extra_cuts" : [
                        "cut::TwoSidedCut('matchPt', 5, 10)"
                    ]
                }
            ],
            "variables" : [
                "var::RelativeResolutionVariable('matchPt','pt')"
            ],
            "override_filenames" : [
                "dpt_binned_by_pt"
            ],
            "weights" : [
                "wt_nominal"
            ],
            "cut" : [
                "cut::GreaterThanCut('puppiWeight', 0.99)",
                "cut::LessThanCut(var::AbsVariable('dz'), 0.2)",
                "cut::EqualsCut('nMatches', 1)"
            ],
            "binning" : "auto",
            "plotspath" : "ANplots/matching/",
            "plotsprefix" : "",
            "driver" : "plot_histogram",
            "force_range" : [-0.2, 0.2],
            "nopad" : true
        }
    ]
}